cryptobaker/__init__.py
cryptobaker/recipes/__init__.py
cryptobaker/recipes/encoding.py
cryptobaker/recipes/encryption.py
cryptobaker/recipes/errors.py
cryptobaker/recipes/hashing.py
cryptobaker/recipes/manip.py
cryptobaker/recipes/util.py
CryptoBaker-0.8.1.dist-info/METADATA
CryptoBaker-0.8.1.dist-info/WHEEL
CryptoBaker-0.8.1.dist-info/top_level.txt
CryptoBaker-0.8.1.dist-info/RECORD
