Metadata-Version: 2.1
Name: CryptoBaker
Version: 0.8.1
Summary: Crypto Bakery
Home-page: https://github.com/AgeOfMarcus/CryptoBaker
Author: AgeOfMarcus
Author-email: marcus@marcusweinberger.com
License: UNKNOWN
Platform: UNKNOWN
Requires-Dist: hexdump
